{
   "dates":["2013", "2014", "2015", "2016", "2017", "2018", "2019", "2020"],
   "metadata": [
      {
        "year": 2013,
        "location": ["ALLEN, Ohio", "NELSON, Virginia", "ST LOUIS, Missouri"],
        "count": [2, 1, 6]
      },
      {
        "year": 2014,
        "location": ["ARAPAHOE, Colorado","ARAPAHOE, Colorado",
         "BEXAR, Texas",
         "BOONE, Missouri",
         "CHAMBERS, Texas",
         "COLLIER, Florida",
         "COOK, Illinois",
         "HARRIS, Texas",
         "HILLSBOROUGH, Florida",
         "HORRY, South Carolina",
         "INDIAN RIVER, Florida",
         "JEFFERSON, Colorado",
         "JIM HOGG, Texas",
         "JIM WELLS, Texas",
         "JOHNSON, Tennessee",
         "LA SALLE, Texas",
         "LEE, Florida",
         "MADISON, Illinois",
         "MANATEE, Florida",
         "ORANGE, Florida",
         "OSCEOLA, Florida",
         "POLK, Minnesota",
         "RANDOLPH, Illinois",
         "SANGAMON, Illinois",
         "SMITH, Texas",
         "ST LOUIS, Missouri",
         "WILLACY, Texas"
         ],
        "count": [4,3, 1, 2, 12, 1, 8, 4, 1, 3, 1, 1, 3, 1, 1, 1, 2, 1, 5, 4, 1, 2, 8, 1, 2, 5]
      },
     
      {
        "year": 2015,
        "location": ["ALLEN, Ohio", "ANOKA, Minnesota", "ARAPAHOE, Colorado", "BEE, Texas", "BENTON, Washington", "BEXAR, Texas", "CARVER, Minnesota", "FAYETTE, Tennessee",
         "FILLMORE, Minnesota", "FLOYD, Texas", "FREDERICK, Maryland", "GRAINGER, Tennessee", "GREENVILLE, South Carolina", "HARRIS, Texas", "HENRICO, Virginia", "HOWARD, Maryland",
         "INGHAM, Michigan", "JIM WELLS, Texas", "KIMBLE, Texas", "LAURENS, South Carolina", "MONTGOMERY, Maryland", "NEWTON, Texas", "NICOLLET, Minnesota", "SHELBY, Tennessee",
         "ST LOUIS, Missouri", "STEARNS, Minnesota", "WILLACY, Texas"],
        "count": [2, 2, 5, 1, 1, 1, 3, 1, 1, 1, 1, 1, 10, 18, 2, 3, 4, 5, 1, 1, 5, 2, 2, 1, 6, 1, 9]
       },
   
      {
        "year": 2016,
        "location": ["ALACHUA, Florida", "ALLEN, Ohio", "ANNE ARUNDEL, Maryland", "ARAPAHOE, Colorado", "BELTRAMI, Minnesota", "BEXAR, Texas", "BOSQUE, Texas", "CARBON, Wyoming",
         "CHAMPAIGN, Illinois", "CHEROKEE, Oklahoma", "CLACKAMAS, Oregon", "COLLIER, Florida", "COOKE, Texas", "EATON, Michigan", "ESCAMBIA, Florida", "FORT BEND, Texas", 
         "GREENVILLE, South Carolina", "GREGG, Texas", "HARRIS, Texas", "HENRICO, Virginia", "HIDALGO, Texas", "HILLSBOROUGH, Florida", "HOWARD, Maryland", "HUTCHINSON, Texas",
         "JEFFERSON, Louisiana", "JIM WELLS, Texas", "JOHNSON, Tennessee", "KENT, Delaware", "KITSAP, Washington", "KLEBERG, Texas", "LEE, Florida", "MCKENZIE, North Dakota",
         "MIAMI-DADE, Florida", "MONTGOMERY, Maryland", "NOLAN, Texas", "ORANGE, Florida", "OSCEOLA, Florida", "OTTER TAIL, Minnesota", "PALM BEACH, Florida", "RANDOLPH, Illinois",
         "ROOSEVELT, Montana", "SEMINOLE, Florida", "ST LOUIS, Minnesota", "ST LOUIS, Missouri", "SUSSEX, Delaware", "TANGIPAHOA, Louisiana", "VOLUSIA, Florida", "WHITE, Arkansas",
         "WILLACY, Texas", "WINNEBAGO, Illinois"],
        "count": [1, 1, 2, 3, 1, 1, 1, 2, 1, 1, 1, 4, 1, 1, 2, 2, 13, 1, 23, 7, 1, 2, 6, 3, 114, 1, 1, 2, 1, 8, 4, 1, 42, 1, 1, 3, 1, 1, 9, 2, 1, 3, 1, 11, 10, 1, 2, 2, 20, 1]
      },
   
      {
        "year": 2017,
        "location": ["ARAPAHOE, Colorado", "AUSTIN, Texas", "BEXAR, Texas", "BLUE EARTH, Minnesota", "BOWIE, Texas", "BOX ELDER, Utah", "BRAZOS, Texas", "BROWN, Wisconsin",
         "CALEDONIA, Vermont", "CALHOUN, Michigan", "CAMDEN, Missouri", "CARVER, Minnesota", "CHAMBERS, Texas", "CHESTER, South Carolina", "CHITTENDEN, Vermont", "CLAIBORNE, Tennessee",
         "CROCKETT, Tennessee", "CROW WING, Minnesota", "DANE, Wisconsin", "DOUGLAS, Colorado", "FRANKLIN, Kentucky", "GALLATIN, Montana", "GREENVILLE, South Carolina",
         "HARDEMAN, Tennessee", "HARRIS, Texas", "HENNEPIN, Minnesota", "HENRICO, Virginia", "HIDALGO, Texas", "HOPKINS, Texas", "HOUSTON, Minnesota", "INGHAM, Michigan",
         "JACKSON, Michigan", "JEFFERSON, Colorado", "JEFFERSON, Louisiana", "KALAMAZOO, Michigan", "KANKAKEE, Illinois", "KENT, Delaware", "KITSAP, Washington", "KNOX, Tennessee",
         "LAFAYETTE, Louisiana", "LARIMER, Colorado", "LENAWEE, Michigan", "MACKINAC, Michigan", "MADISON, Illinois", "MADISON, Tennessee", "MAURY, Tennessee", "MONROE, Tennessee",
         "MORTON, North Dakota", "NORFOLK, Massachusetts", "PICKENS, South Carolina", "PINAL, Arizona", "RANDALL, Texas", "RANDOLPH, Illinois", "SALUDA, South Carolina",
         "SHELBY, Tennessee", "ST LOUIS, Missouri", "ST TAMMANY, Louisiana", "STARR, Texas", "STONE, Missouri", "SUSSEX, Delaware", "SWEETWATER, Wyoming", "WARD, North Dakota",
         "WARREN, Kentucky", "WASHINGTON, Minnesota", "WASHINGTON, Oregon", "WASHTENAW, Michigan", "WAYNE, Michigan", "WEBB, Texas", "WILLACY, Texas", "WINNEBAGO, Illinois",
         "WINONA, Minnesota"],
        "count": [2, 1, 1, 10, 1, 1, 1, 12, 1, 1, 1, 3, 4, 1, 2, 1, 1, 1, 3, 1, 52, 1, 20, 1, 25, 1, 5, 1, 1, 4, 1, 1, 3, 51, 1, 1, 4, 1, 1, 1, 1, 1, 1, 2, 1, 1, 1, 2, 2, 1, 7, 1,
         1, 1, 2, 16, 1, 1, 1, 1, 1, 1, 1, 1, 1, 1, 1, 43, 6, 2, 2]
         },
   
      {
        "year": 2018, 
        "location": ["ADAMS, Colorado", "ALLEN, Kentucky", "BAY, Michigan", "BENSON, North Dakota", "BERKELEY, West Virginia", "BERRIEN, Michigan", "BEXAR, Texas", 
         "BOLLINGER, Missouri", "BOULDER, Colorado", "BULLITT, Kentucky", "BURNET, Texas", "CARROLL, Virginia", "CHAMBERS, Texas", "CHEROKEE, South Carolina", "CHESTERFIELD, South Carolina",
         "CLINTON, Michigan", "COLLIER, Florida", "COMAL, Texas", "CREEK, Oklahoma", "DALLAS, Texas", "DODGE, Wisconsin", "DUBOIS, Indiana", "EL PASO, Colorado", "FAYETTE, West Virginia",
         "FORT BEND, Texas", "FRANKLIN, Kentucky", "FRANKLIN, Vermont", "FREEBORN, Minnesota", "GENESEE, Michigan", "GREENVILLE, South Carolina", "HAMILTON, Tennessee",
         "HARRIS, Texas", "HARRISON, Mississippi", "HENNEPIN, Minnesota", "HENRICO, Virginia", "HERNANDO, Florida", "HILLSBOROUGH, Florida", "HORRY, South Carolina",
         "INGHAM, Michigan", "IOSCO, Michigan", "ISANTI, Minnesota", "JACKSON, Michigan", "JEFFERSON, Colorado", "JEFFERSON, Louisiana", "JIM WELLS, Texas", "KALAMAZOO, Michigan",
         "KANKAKEE, Illinois", "KENT, Michigan", "KING, Washington", "KITSAP, Washington", "KNOX, Illinois", "LAFAYETTE, Louisiana", "LAKE, Florida", "LAURENS, South Carolina",
         "LEE, Florida", "LINCOLN, Wisconsin", "MACOMB, Michigan", "MANATEE, Florida", "MARION, Indiana", "MARION, Tennessee", "MARSHALL, Minnesota", "MARTIN, Minnesota",
         "MIDLAND, Texas", "MISSAUKEE, Michigan", "MONTGOMERY, Tennessee", "MONTGOMERY, Texas", "NEW CASTLE, Delaware", "NODAWAY, Missouri", "ONEIDA, Wisconsin",  "ORANGE, Florida",
         "OSCEOLA, Florida", "OSCEOLA, Michigan", "PALM BEACH, Florida", "PASCO, Florida", "PIMA, Arizona", "PINAL, Arizona", "POLK, Florida", "PRINCE WILLIAM, Virginia", 
         "PUTNAM, Indiana", "RAMSEY, Minnesota", "RICE, Minnesota", "SAGINAW, Michigan", "SARASOTA, Florida", "SCHOOLCRAFT, Michigan", "SEMINOLE, Florida", "ST JOSEPH, Michigan",
         "ST LOUIS, Missouri", "ST LUCIE, Florida", "STARR, Texas", "STEARNS, Minnesota", "STONE, Missouri", "SUSSEX, Delaware", "SWEETWATER, Wyoming", "TARRANT, Texas", 
         "TULSA, Oklahoma", "VICTORIA, Texas", "VOLUSIA, Florida", "WASHINGTON, Vermont", "WAYNE, Michigan", "WEBB, Texas", "WILLACY, Texas", "WRIGHT, Minnesota"],
        "count": [1, 1, 1, 1, 2, 1, 1, 1, 1, 1, 10, 1, 2, 1, 1, 1, 4, 1, 1, 1, 1, 1, 1, 1, 1, 5, 1, 1, 4, 2, 1, 13, 1, 7, 3, 11, 6, 1, 2, 1, 1, 2, 1, 3, 10, 1, 1, 1, 2, 1,
         1, 6, 1, 2, 1, 1, 1, 1, 1, 1, 3, 1, 1, 1, 1, 2, 3, 1, 1, 1, 6, 1, 1, 20, 3, 1, 2, 1, 3, 2, 1, 1, 1, 1, 1, 1, 2, 11, 1, 2, 2, 1, 3, 4, 34, 1, 1, 1, 1, 5, 6, 2, 2]
      },
   
     
      {
        "year": "2019",
        "location": ["ACCOMACK, Virginia", "ALBEMARLE, Virginia", "ALLEN, Kentucky", "ALLEN, Ohio", "AMHERST, Virginia", "ANNE ARUNDEL, Maryland", "ARAPAHOE, Colorado",
         "ARLINGTON, Virginia", "BAKER, Florida", "BALTIMORE, Maryland", "BELL, Texas", "BERKELEY, West Virginia", "BERNALILLO, New Mexico", "BEXAR, Texas", "BOSSIER, Louisiana",
         "BOWIE, Texas", "BRADLEY, Tennessee", "BRAXTON, West Virginia", "BROOKE, West Virginia", "BROWN, Wisconsin", "CARSON CITY, Nevada", "CATAWBA, North Carolina",
         "CHAMBERS, Texas", "CHEROKEE, Georgia", "CHESTERFIELD, Virginia", "CHITTENDEN, Vermont", "CLAY, Indiana", "CLAYTON, Georgia", "CLEVELAND, North Carolina", "COBB, Georgia",
         "COLLIER, Florida", "CONCHO, Texas", "COOKE, Texas", "COWETA, Georgia", "CUMBERLAND, North Carolina", "DEKALB, Georgia", "DODDRIDGE, West Virginia", "DODGE, Wisconsin",
         "DOUGLAS, Colorado", "DOUGLAS, Nebraska", "DUPAGE, Illinois", "EAU CLAIRE, Wisconsin", "EDWARDS, Texas", "ELLIS, Texas", "FANNIN, Georgia", "FAYETTE, West Virginia",
         "FLAGLER, Florida", "FRANKLIN, Kentucky", "FULTON, Georgia", "GENESEE, Michigan", "GEORGETOWN, South Carolina", "GILMER, West Virginia", "GRAHAM, North Carolina",
         "GRAND FORKS, North Dakota", "GREEN LAKE, Wisconsin", "GREENBRIER, West Virginia", "GREENVILLE, South Carolina", "HALL, Georgia", "HAMPSHIRE, West Virginia",
         "HARFORD, Maryland", "HARRIS, Texas", "HAYWOOD, North Carolina", "HENNEPIN, Minnesota", "HENRICO, Virginia", "HERNANDO, Florida", "HILLSBOROUGH, Florida", "HOPKINS, Texas",
         "HORRY, South Carolina",  "HOWARD, Maryland", "HUBBARD, Minnesota", "HUNT, Texas", "HUNTINGTON, Indiana", "ISANTI, Minnesota", "ITASCA, Minnesota", "JACKSON, Michigan",
         "JACKSON, North Carolina", "JEFFERSON, Colorado", "JEFFERSON, Louisiana", "JIM WELLS, Texas", "JOHNSTON, North Carolina", "KIMBLE, Texas", "KING, Washington", "KIOWA, Colorado",
         "KNOX, Kentucky", "LACLEDE, Missouri", "LAFAYETTE, Louisiana", "LAKE, Illinois", "LAPEER, Michigan", "LEE, Florida", "LEE, Virginia", "LINCOLN, West Virginia",
         "LOGAN, West Virginia", "LUNENBURG, Virginia", "MACKINAC, Michigan", "MACOMB, Michigan", "MARION, Indiana", "MARION, West Virginia", "MARSHALL, West Virginia",
         "MASON, West Virginia", "MATHEWS, Virginia", "MAUI, Hawaii", "MERCER, West Virginia", "MONTGOMERY, Ohio", "MONTGOMERY, Texas", "MORGAN, West Virginia", "MULTNOMAH, Oregon",
         "MUSKEGON, Michigan", "NEW CASTLE, Delaware", "NEW HANOVER, North Carolina", "NICHOLAS, West Virginia", "OHIO, West Virginia", "ONEIDA, Wisconsin", "ORANGE, Florida",
         "OUTAGAMIE, Wisconsin", "PALM BEACH, Florida", "PASCO, Florida",  "PAULDING, Georgia", "PEACH, Georgia", "PIERCE, Georgia", "PIKE, Kentucky", "PINE, Minnesota", 
         "POCAHONTAS, West Virginia", "PONTOTOC, Mississippi", "PRINCE GEORGE'S, Maryland", "PRINCE WILLIAM, Virginia", "RALEIGH, West Virginia", "RANDOLPH, Illinois", 
         "RANDOLPH, West Virginia", "RICHLAND, South Carolina", "RITCHIE, West Virginia", "ROANE, West Virginia", "ROSEAU, Minnesota", "RUTHERFORD, Tennessee", "SAN PATRICIO, Texas",
         "SCOTLAND, North Carolina", "SEMINOLE, Florida", "SHELBY, Tennessee", "SPOKANE, Washington", "ST LOUIS, Minnesota", "ST LOUIS, Missouri", "ST TAMMANY, Louisiana", 
         "STAFFORD, Virginia", "STEVENS, Minnesota", "SUMMERS, West Virginia", "SUSSEX, Delaware", "SWISHER, Texas", "TARRANT, Texas", "TWIGGS, Georgia", "UNION, South Carolina",
         "VIGO, Indiana", "VOLUSIA, Florida", "WARD, North Dakota", "WARREN, Virginia", "WASHINGTON, Oregon", "WAYNE, Michigan", "WAYNE, West Virginia", "WEBB, Texas", "WEBSTER, Louisiana",
         "HITFIELD, Georgia", "WINNEBAGO, Illinois", "WINNEBAGO, Wisconsin", "WOOD, West Virginia", "WYOMING, West Virginia", "ZAVALA, Texas"],
       "count": [ 1, 1, 1, 6, 1, 8, 2, 3, 1, 2, 3, 13, 2, 3, 1, 1, 4, 2, 2, 4, 1, 4, 1, 1, 1, 4, 1, 1, 1, 1, 3, 1, 1, 11, 11, 1, 3, 2, 2, 3, 1, 1, 4, 1, 1, 1, 1, 28, 2, 43, 1,
         1, 1, 1, 2, 1, 11, 2, 1, 2, 10, 4, 7, 22, 1, 9, 1, 1, 9, 1, 5, 2, 1, 1, 1, 1, 2, 6, 4, 1, 1, 4, 3, 1, 2, 1, 2, 2, 12, 1, 1, 3, 1, 1, 1, 1, 1, 1, 1, 1, 1, 2, 2, 2, 1, 1, 1,
         5, 1, 2, 1, 2, 6, 1, 28, 4, 15, 2, 2, 1, 1, 1, 1, 9, 7, 7, 2, 5, 1, 3, 3, 1, 2, 1, 1, 2, 1, 1, 1, 9, 1, 1, 1, 1, 14, 1, 13, 1, 1, 3, 1, 1, 1, 2, 1, 1, 22, 1, 2, 2, 1, 4,
         1, 1]
      },
   
   
      {
        "year": "2020",
        "location": ["ACCOMACK, Virginia", "ADAMS, Nebraska", "ALLEGHENY, Pennsylvania", "ALLEN, Ohio", "ANNE ARUNDEL, Maryland", "ASHLAND, Ohio",
         "ATASCOSA, Texas", "BAKER, Florida", "BALTIMORE, Maryland", "BEE, Texas", "BELL, Texas", "BERKELEY, South Carolina", "BERKELEY, West Virginia", "BEXAR, Texas", 
         "BIBB, Georgia", "BOONE, Kentucky", "BOONE, West Virginia", "BOSSIER, Louisiana", "BOX ELDER, Utah", "BRANTLEY, Georgia", "BRAXTON, West Virginia","BROOKE, West Virginia",
         "BURNETT, Wisconsin", "CAMDEN, Missouri", "CAMPBELL, Wyoming", "CAROLINE, Virginia", "CARROLL, Virginia", "CARSON CITY, Nevada", "CARVER, Minnesota", "CASTRO, Texas",
         "CATAWBA, North Carolina", "CHAMBERS, Texas", "CHARLEVOIX, Michigan", "CHEROKEE, Georgia", "CHESTERFIELD, Virginia", "CLARK, Washington", "CLAYTON, Georgia",
         "COBB, Georgia", "COFFEE, Georgia", "COLLIER, Florida", "COOK, Illinois", "COOKE, Texas", "COWETA, Georgia", "CRAWFORD, Georgia", "CRAWFORD, Michigan", "CULPEPER, Virginia",
         "CUMBERLAND, North Carolina", "CUMBERLAND, Virginia", "DEKALB, Georgia", "DODGE, Georgia", "DOUGLAS, Colorado", "DOUGLAS, Georgia", "DURHAM, North Carolina",
         "EDWARDS, Texas", "EFFINGHAM, Georgia", "EL PASO, Texas", "ELLIS, Texas", "FAIRFAX, Virginia", "FAYETTE, West Virginia", "FLAGLER, Florida", "FLOYD, Georgia", "FORT BEND, Texas",
         "FRANKLIN, Kentucky", "FULTON, Georgia", "GALVESTON, Texas", "GENESEE, Michigan", "GOLIAD, Texas", "GREENVILLE, South Carolina", "HALL, Georgia", "HAMILTON, Tennessee",
         "HARDY, West Virginia", "HARFORD, Maryland", "HARRIS, Texas", "HAYWOOD, North Carolina", "HENNEPIN, Minnesota", "HENRICO, Virginia", "HERNANDO, Florida", "HILLSBOROUGH, Florida",
         "HILLSDALE, Michigan", "HOPKINS, Texas", "HORRY, South Carolina", "HOWARD, Maryland", "INGHAM, Michigan", "JACKSON, Michigan", "JASPER, Missouri", "JEFFERSON, Louisiana",
         "KANAWHA, West Virginia", "KENT, Michigan", "KOSCIUSKO, Indiana", "LAKE OF THE WOODS, Minnesota", "LANCASTER, South Carolina", "LEE, Florida", "LEWIS, West Virginia",
         "LEXINGTON, South Carolina", "LINCOLN, West Virginia", "LOGAN, West Virginia", "LOWNDES, Georgia", "MACOMB, Michigan", "MARATHON, Wisconsin", "MARSHALL, West Virginia",
         "MASON, West Virginia", "MCDONALD, Missouri", "MCLEAN, North Dakota", "MERCER, West Virginia", "MERIWETHER, Georgia", "MERRIMACK, New Hampshire", "MILLE LACS, Minnesota",
         "MINERAL, West Virginia", "MONONGALIA, West Virginia", "MONROE, Indiana", "MONTGOMERY, Maryland", "MONTGOMERY, Ohio", "MONTGOMERY, Tennessee", "MORGAN, West Virginia",
         "MORTON, North Dakota", "MULTNOMAH, Oregon", "MUSCOGEE, Georgia", "NEW CASTLE, Delaware", "NEWTON, Georgia", "NICHOLAS, West Virginia", "NYE, Nevada", "OAKLAND, Michigan",
         "ORANGE, Florida", "OUTAGAMIE, Wisconsin", "PALM BEACH, Florida", "PASCO, Florida", "PATRICK, Virginia", "PAULDING, Georgia", "PERSON, North Carolina", "PICKAWAY, Ohio",
         "PIERCE, Washington", "PITTSYLVANIA, Virginia", "PRINCE GEORGE'S, Maryland", "PRINCE GEORGE, Virginia", "PULASKI, Arkansas", "RACINE, Wisconsin", "RALEIGH, West Virginia",
         "RANDOLPH, Illinois", "RITCHIE, West Virginia", "ROANOKE, Virginia", "RUSSELL, Virginia", "RUTHERFORD, Tennessee", "SALINE, Missouri", "SAN PATRICIO, Texas", 
         "SCOTT, Virginia", "SEMINOLE, Florida", "SHEBOYGAN, Wisconsin", "SHELBY, Tennessee", "SHELBY, Texas", "SHERBURNE, Minnesota", "SHIAWASSEE, Michigan", 
         "SOUTHAMPTON, Virginia", "SPOKANE, Washington", "ST CHARLES, Missouri", "ST LOUIS, Minnesota", "ST LOUIS, Missouri", "STAFFORD, Virginia", "SUMMIT, Ohio", "SUSSEX, Delaware",
         "TARRANT, Texas", "TAZEWELL, Virginia", "THOMAS, Georgia", "TYLER, West Virginia", "UPSHUR, West Virginia","OLUSIA, Florida", "WARD, North Dakota", "WASHINGTON, Minnesota",
          "WASHINGTON, Oregon", "WASHOE, Nevada", "WAYNE, Michigan", "WAYNE, West Virginia", "WEBB, Texas", "WHITFIELD, Georgia", "WOOD, West Virginia", "WRIGHT, Minnesota", 
          "WYOMING, West Virginia", "ZAVALA, Texas"],
          "count": [3, 1, 2, 1, 2, 1, 8, 1, 1, 1, 1, 1, 10, 1, 8, 1, 3, 1, 2, 3, 1, 1, 1, 1, 1, 1, 1, 1, 1, 1, 2, 3, 1, 1, 4, 1, 8, 16, 1, 3, 1, 3, 10, 1, 1, 1, 4, 1, 27, 1, 1, 6,
           1, 43, 1, 1, 3, 1, 1, 1, 22, 6, 3, 1, 1, 20, 1, 3, 1, 1, 2, 1, 93, 2, 1, 25, 1, 25, 1, 1, 3, 7, 2, 1, 1, 1, 10, 1, 1, 1, 2, 14, 2, 4, 1, 2, 10, 2, 2, 2, 3, 1, 1, 1, 1,
           2, 1, 2, 3, 1, 3, 5, 4, 4, 1, 1, 7, 4, 1, 1, 1, 1, 14, 1, 96, 5, 2, 18, 1, 1, 1, 2, 2, 1, 1, 2, 1, 1, 1, 1, 1, 1, 1, 2, 1, 2, 2, 1, 1, 1, 3, 1, 2, 1, 3, 6, 3, 1, 2, 4, 2, 
           3, 2, 1, 7, 1, 3, 1, 3, 2, 1, 17, 2, 1, 1, 1, 2]
        }
     ]
   }   
   